selenium_aurelia/__init__.py
selenium_aurelia/test/__init__.py
selenium_aurelia/test/example.py
selenium_aurelia/test/test_driver.py
selenium_aurelia-0.1.0.dist-info/DESCRIPTION.rst
selenium_aurelia-0.1.0.dist-info/METADATA
selenium_aurelia-0.1.0.dist-info/RECORD
selenium_aurelia-0.1.0.dist-info/WHEEL
selenium_aurelia-0.1.0.dist-info/metadata.json
selenium_aurelia-0.1.0.dist-info/top_level.txt
