Metadata-Version: 2.0
Name: selenium-aurelia
Version: 0.1.0
Summary: Wrapper around selenium driver to ease testing of Aurelia based applications.
Home-page: https://framagit.org/Jenselme/selenium-aurelia
Author: Julien Enselme
Author-email: julien.enselme@centrale-marseille.fr
License: MIT
Keywords: selenium aurelia
Platform: UNKNOWN
Classifier: Development Status :: 3 - Alpha
Classifier: Intended Audience :: Developers
Classifier: License :: OSI Approved
Classifier: License :: OSI Approved :: MIT License
Classifier: Topic :: Internet :: WWW/HTTP :: Browsers
Classifier: Topic :: Software Development :: Testing
Classifier: Topic :: Utilities
Classifier: Programming Language :: Python :: 3
Classifier: Programming Language :: Python :: 3.3
Classifier: Programming Language :: Python :: 3.4
Classifier: Programming Language :: Python :: 3.5
Requires-Dist: selenium (>=2.50.0)
